{"frames":{"3":{"frame":{"x":179,"y":775,"w":82,"h":51},"rotated":false,"trimmed":false,"spriteSourceSize":{"x":0,"y":0,"w":82,"h":51},"sourceSize":{"w":82,"h":51}},"sprite1":{"frame":{"x":846,"y":2,"w":121,"h":43},"rotated":false,"trimmed":false,"spriteSourceSize":{"x":0,"y":0,"w":121,"h":43},"sourceSize":{"w":121,"h":43}},"levelup004":{"frame":{"x":194,"y":5,"w":65,"h":78},"rotated":false,"trimmed":false,"spriteSourceSize":{"x":0,"y":0,"w":65,"h":78},"sourceSize":{"w":65,"h":78}},"levelup008":{"frame":{"x":478,"y":5,"w":63,"h":78},"rotated":false,"trimmed":false,"spriteSourceSize":{"x":0,"y":0,"w":63,"h":78},"sourceSize":{"w":63,"h":78}},"levelup003":{"frame":{"x":118,"y":8,"w":65,"h":75},"rotated":false,"trimmed":false,"spriteSourceSize":{"x":0,"y":0,"w":65,"h":75},"sourceSize":{"w":65,"h":75}},"levelup007":{"frame":{"x":413,"y":22,"w":54,"h":61},"rotated":false,"trimmed":false,"spriteSourceSize":{"x":0,"y":0,"w":54,"h":61},"sourceSize":{"w":54,"h":61}},"levelup006":{"frame":{"x":346,"y":26,"w":49,"h":57},"rotated":false,"trimmed":false,"spriteSourceSize":{"x":0,"y":0,"w":49,"h":57},"sourceSize":{"w":49,"h":57}},"stand001":{"frame":{"x":560,"y":28,"w":27,"h":55},"rotated":false,"trimmed":false,"spriteSourceSize":{"x":0,"y":0,"w":27,"h":55},"sourceSize":{"w":27,"h":55}},"levelup005":{"frame":{"x":275,"y":31,"w":53,"h":52},"rotated":false,"trimmed":false,"spriteSourceSize":{"x":0,"y":0,"w":53,"h":52},"sourceSize":{"w":53,"h":52}},"levelup001":{"frame":{"x":9,"y":36,"w":31,"h":47},"rotated":false,"trimmed":false,"spriteSourceSize":{"x":0,"y":0,"w":31,"h":47},"sourceSize":{"w":31,"h":47}},"levelup002":{"frame":{"x":55,"y":36,"w":53,"h":47},"rotated":false,"trimmed":false,"spriteSourceSize":{"x":0,"y":0,"w":53,"h":47},"sourceSize":{"w":53,"h":47}},"sprite11":{"frame":{"x":806,"y":48,"w":203,"h":91},"rotated":false,"trimmed":false,"spriteSourceSize":{"x":0,"y":0,"w":203,"h":91},"sourceSize":{"w":203,"h":91}},"sprite12":{"frame":{"x":297,"y":103,"w":26,"h":56},"rotated":false,"trimmed":false,"spriteSourceSize":{"x":0,"y":0,"w":26,"h":56},"sourceSize":{"w":26,"h":56}},"sprite23213":{"frame":{"x":7,"y":104,"w":27,"h":55},"rotated":false,"trimmed":false,"spriteSourceSize":{"x":0,"y":0,"w":27,"h":55},"sourceSize":{"w":27,"h":55}},"sprite14":{"frame":{"x":170,"y":104,"w":27,"h":55},"rotated":false,"trimmed":false,"spriteSourceSize":{"x":0,"y":0,"w":27,"h":55},"sourceSize":{"w":27,"h":55}},"sprite15":{"frame":{"x":52,"y":106,"w":28,"h":53},"rotated":false,"trimmed":false,"spriteSourceSize":{"x":0,"y":0,"w":28,"h":53},"sourceSize":{"w":28,"h":53}},"sprite16":{"frame":{"x":211,"y":107,"w":30,"h":52},"rotated":false,"trimmed":false,"spriteSourceSize":{"x":0,"y":0,"w":30,"h":52},"sourceSize":{"w":30,"h":52}},"sprite17":{"frame":{"x":99,"y":108,"w":29,"h":51},"rotated":false,"trimmed":false,"spriteSourceSize":{"x":0,"y":0,"w":29,"h":51},"sourceSize":{"w":29,"h":51}},"sprite18":{"frame":{"x":147,"y":133,"w":7,"h":7},"rotated":false,"trimmed":false,"spriteSourceSize":{"x":0,"y":0,"w":7,"h":7},"sourceSize":{"w":7,"h":7}},"sprite19":{"frame":{"x":273,"y":133,"w":7,"h":7},"rotated":false,"trimmed":false,"spriteSourceSize":{"x":0,"y":0,"w":7,"h":7},"sourceSize":{"w":7,"h":7}},"sprite20":{"frame":{"x":521,"y":172,"w":28,"h":55},"rotated":false,"trimmed":false,"spriteSourceSize":{"x":0,"y":0,"w":28,"h":55},"sourceSize":{"w":28,"h":55}},"sprite21":{"frame":{"x":559,"y":172,"w":28,"h":55},"rotated":false,"trimmed":false,"spriteSourceSize":{"x":0,"y":0,"w":28,"h":55},"sourceSize":{"w":28,"h":55}},"sprite22":{"frame":{"x":10,"y":174,"w":31,"h":53},"rotated":false,"trimmed":false,"spriteSourceSize":{"x":0,"y":0,"w":31,"h":53},"sourceSize":{"w":31,"h":53}},"sprite23":{"frame":{"x":441,"y":175,"w":34,"h":52},"rotated":false,"trimmed":false,"spriteSourceSize":{"x":0,"y":0,"w":34,"h":52},"sourceSize":{"w":34,"h":52}},"sprite24":{"frame":{"x":52,"y":176,"w":34,"h":51},"rotated":false,"trimmed":false,"spriteSourceSize":{"x":0,"y":0,"w":34,"h":51},"sourceSize":{"w":34,"h":51}},"sprite25":{"frame":{"x":606,"y":176,"w":19,"h":51},"rotated":false,"trimmed":false,"spriteSourceSize":{"x":0,"y":0,"w":19,"h":51},"sourceSize":{"w":19,"h":51}},"sprite26":{"frame":{"x":389,"y":178,"w":39,"h":49},"rotated":false,"trimmed":false,"spriteSourceSize":{"x":0,"y":0,"w":39,"h":49},"sourceSize":{"w":39,"h":49}},"run001":{"frame":{"x":127,"y":184,"w":35,"h":43},"rotated":false,"trimmed":false,"spriteSourceSize":{"x":0,"y":0,"w":35,"h":43},"sourceSize":{"w":35,"h":43}},"sprite28":{"frame":{"x":602,"y":185,"w":3,"h":14},"rotated":false,"trimmed":false,"spriteSourceSize":{"x":0,"y":0,"w":3,"h":14},"sourceSize":{"w":3,"h":14}},"sprite9":{"frame":{"x":190,"y":190,"w":44,"h":37},"rotated":false,"trimmed":false,"spriteSourceSize":{"x":0,"y":0,"w":44,"h":37},"sourceSize":{"w":44,"h":37}},"sprite30":{"frame":{"x":250,"y":191,"w":51,"h":29},"rotated":false,"trimmed":false,"spriteSourceSize":{"x":0,"y":0,"w":51,"h":29},"sourceSize":{"w":51,"h":29}},"sprite31":{"frame":{"x":307,"y":195,"w":51,"h":22},"rotated":false,"trimmed":false,"spriteSourceSize":{"x":0,"y":0,"w":51,"h":22},"sourceSize":{"w":51,"h":22}},"sprite32":{"frame":{"x":626,"y":196,"w":1,"h":3},"rotated":false,"trimmed":false,"spriteSourceSize":{"x":0,"y":0,"w":1,"h":3},"sourceSize":{"w":1,"h":3}},"sprite33":{"frame":{"x":371,"y":199,"w":7,"h":7},"rotated":false,"trimmed":false,"spriteSourceSize":{"x":0,"y":0,"w":7,"h":7},"sourceSize":{"w":7,"h":7}},"sprite34":{"frame":{"x":650,"y":199,"w":7,"h":7},"rotated":false,"trimmed":false,"spriteSourceSize":{"x":0,"y":0,"w":7,"h":7},"sourceSize":{"w":7,"h":7}},"sprite35":{"frame":{"x":601,"y":203,"w":1,"h":8},"rotated":false,"trimmed":false,"spriteSourceSize":{"x":0,"y":0,"w":1,"h":8},"sourceSize":{"w":1,"h":8}},"sprite36":{"frame":{"x":627,"y":205,"w":1,"h":5},"rotated":false,"trimmed":false,"spriteSourceSize":{"x":0,"y":0,"w":1,"h":5},"sourceSize":{"w":1,"h":5}},"sprite37":{"frame":{"x":166,"y":211,"w":23,"h":16},"rotated":false,"trimmed":false,"spriteSourceSize":{"x":0,"y":0,"w":23,"h":16},"sourceSize":{"w":23,"h":16}},"sprite38":{"frame":{"x":87,"y":217,"w":24,"h":10},"rotated":false,"trimmed":false,"spriteSourceSize":{"x":0,"y":0,"w":24,"h":10},"sourceSize":{"w":24,"h":10}},"jump003":{"frame":{"x":102,"y":244,"w":30,"h":48},"rotated":false,"trimmed":false,"spriteSourceSize":{"x":0,"y":0,"w":30,"h":48},"sourceSize":{"w":30,"h":48}},"jump005":{"frame":{"x":188,"y":245,"w":27,"h":57},"rotated":false,"trimmed":false,"spriteSourceSize":{"x":0,"y":0,"w":27,"h":57},"sourceSize":{"w":27,"h":57}},"jump004":{"frame":{"x":146,"y":246,"w":29,"h":54},"rotated":false,"trimmed":false,"spriteSourceSize":{"x":0,"y":0,"w":29,"h":54},"sourceSize":{"w":29,"h":54}},"jump002":{"frame":{"x":56,"y":250,"w":31,"h":52},"rotated":false,"trimmed":false,"spriteSourceSize":{"x":0,"y":0,"w":31,"h":52},"sourceSize":{"w":31,"h":52}},"sprite43":{"frame":{"x":300,"y":255,"w":30,"h":47},"rotated":false,"trimmed":false,"spriteSourceSize":{"x":0,"y":0,"w":30,"h":47},"sourceSize":{"w":30,"h":47}},"jump001":{"frame":{"x":10,"y":256,"w":34,"h":46},"rotated":false,"trimmed":false,"spriteSourceSize":{"x":0,"y":0,"w":34,"h":46},"sourceSize":{"w":34,"h":46}},"jump006":{"frame":{"x":228,"y":256,"w":34,"h":46},"rotated":false,"trimmed":false,"spriteSourceSize":{"x":0,"y":0,"w":34,"h":46},"sourceSize":{"w":34,"h":46}},"sprite46":{"frame":{"x":344,"y":257,"w":35,"h":45},"rotated":false,"trimmed":false,"spriteSourceSize":{"x":0,"y":0,"w":35,"h":45},"sourceSize":{"w":35,"h":45}},"sprite47":{"frame":{"x":277,"y":277,"w":7,"h":7},"rotated":false,"trimmed":false,"spriteSourceSize":{"x":0,"y":0,"w":7,"h":7},"sourceSize":{"w":7,"h":7}},"sprite48":{"frame":{"x":402,"y":277,"w":7,"h":7},"rotated":false,"trimmed":false,"spriteSourceSize":{"x":0,"y":0,"w":7,"h":7},"sourceSize":{"w":7,"h":7}},"sprite49":{"frame":{"x":761,"y":284,"w":123,"h":78},"rotated":false,"trimmed":false,"spriteSourceSize":{"x":0,"y":0,"w":123,"h":78},"sourceSize":{"w":123,"h":78}},"attack010":{"frame":{"x":453,"y":322,"w":35,"h":51},"rotated":false,"trimmed":false,"spriteSourceSize":{"x":0,"y":0,"w":35,"h":51},"sourceSize":{"w":35,"h":51}},"attack001":{"frame":{"x":10,"y":323,"w":33,"h":54},"rotated":false,"trimmed":false,"spriteSourceSize":{"x":0,"y":0,"w":33,"h":54},"sourceSize":{"w":33,"h":54}},"attack006":{"frame":{"x":261,"y":323,"w":34,"h":54},"rotated":false,"trimmed":false,"spriteSourceSize":{"x":0,"y":0,"w":34,"h":54},"sourceSize":{"w":34,"h":54}},"attack009":{"frame":{"x":409,"y":323,"w":29,"h":54},"rotated":false,"trimmed":false,"spriteSourceSize":{"x":0,"y":0,"w":29,"h":54},"sourceSize":{"w":29,"h":54}},"attack007":{"frame":{"x":303,"y":326,"w":45,"h":51},"rotated":false,"trimmed":false,"spriteSourceSize":{"x":0,"y":0,"w":45,"h":51},"sourceSize":{"w":45,"h":51}},"attack008":{"frame":{"x":362,"y":326,"w":35,"h":51},"rotated":false,"trimmed":false,"spriteSourceSize":{"x":0,"y":0,"w":35,"h":51},"sourceSize":{"w":35,"h":51}},"attack002":{"frame":{"x":58,"y":327,"w":34,"h":50},"rotated":false,"trimmed":false,"spriteSourceSize":{"x":0,"y":0,"w":34,"h":50},"sourceSize":{"w":34,"h":50}},"attack004":{"frame":{"x":159,"y":327,"w":37,"h":50},"rotated":false,"trimmed":false,"spriteSourceSize":{"x":0,"y":0,"w":37,"h":50},"sourceSize":{"w":37,"h":50}},"attack005":{"frame":{"x":207,"y":327,"w":43,"h":50},"rotated":false,"trimmed":false,"spriteSourceSize":{"x":0,"y":0,"w":43,"h":50},"sourceSize":{"w":43,"h":50}},"attack011":{"frame":{"x":495,"y":328,"w":44,"h":42},"rotated":false,"trimmed":false,"spriteSourceSize":{"x":0,"y":0,"w":44,"h":42},"sourceSize":{"w":44,"h":42}},"attack012":{"frame":{"x":553,"y":328,"w":41,"h":42},"rotated":false,"trimmed":false,"spriteSourceSize":{"x":0,"y":0,"w":41,"h":42},"sourceSize":{"w":41,"h":42}},"attack003":{"frame":{"x":107,"y":330,"w":46,"h":47},"rotated":false,"trimmed":false,"spriteSourceSize":{"x":0,"y":0,"w":46,"h":47},"sourceSize":{"w":46,"h":47}},"attack022":{"frame":{"x":461,"y":401,"w":30,"h":53},"rotated":false,"trimmed":false,"spriteSourceSize":{"x":0,"y":0,"w":30,"h":53},"sourceSize":{"w":30,"h":53}},"attack013":{"frame":{"x":11,"y":404,"w":28,"h":51},"rotated":false,"trimmed":false,"spriteSourceSize":{"x":0,"y":0,"w":28,"h":51},"sourceSize":{"w":28,"h":51}},"attack019":{"frame":{"x":309,"y":404,"w":31,"h":54},"rotated":false,"trimmed":false,"spriteSourceSize":{"x":0,"y":0,"w":31,"h":54},"sourceSize":{"w":31,"h":54}},"attack014":{"frame":{"x":51,"y":405,"w":35,"h":52},"rotated":false,"trimmed":false,"spriteSourceSize":{"x":0,"y":0,"w":35,"h":52},"sourceSize":{"w":35,"h":52}},"attack015":{"frame":{"x":101,"y":405,"w":32,"h":52},"rotated":false,"trimmed":false,"spriteSourceSize":{"x":0,"y":0,"w":32,"h":52},"sourceSize":{"w":32,"h":52}},"attack018":{"frame":{"x":260,"y":405,"w":34,"h":52},"rotated":false,"trimmed":false,"spriteSourceSize":{"x":0,"y":0,"w":34,"h":52},"sourceSize":{"w":34,"h":52}},"attack021":{"frame":{"x":404,"y":405,"w":46,"h":47},"rotated":false,"trimmed":false,"spriteSourceSize":{"x":0,"y":0,"w":46,"h":47},"sourceSize":{"w":46,"h":47}},"attack016":{"frame":{"x":151,"y":407,"w":43,"h":45},"rotated":false,"trimmed":false,"spriteSourceSize":{"x":0,"y":0,"w":43,"h":45},"sourceSize":{"w":43,"h":45}},"attack020":{"frame":{"x":346,"y":408,"w":48,"h":44},"rotated":false,"trimmed":false,"spriteSourceSize":{"x":0,"y":0,"w":48,"h":44},"sourceSize":{"w":48,"h":44}},"attack017":{"frame":{"x":201,"y":409,"w":45,"h":43},"rotated":false,"trimmed":false,"spriteSourceSize":{"x":0,"y":0,"w":45,"h":43},"sourceSize":{"w":45,"h":43}},"sprite72":{"frame":{"x":250,"y":422,"w":1,"h":1},"rotated":false,"trimmed":false,"spriteSourceSize":{"x":0,"y":0,"w":1,"h":1},"sourceSize":{"w":1,"h":1}},"sprite73":{"frame":{"x":247,"y":424,"w":2,"h":2},"rotated":false,"trimmed":false,"spriteSourceSize":{"x":0,"y":0,"w":2,"h":2},"sourceSize":{"w":2,"h":2}},"sprite74":{"frame":{"x":951,"y":471,"w":2,"h":2},"rotated":false,"trimmed":false,"spriteSourceSize":{"x":0,"y":0,"w":2,"h":2},"sourceSize":{"w":2,"h":2}},"sprite75":{"frame":{"x":959,"y":471,"w":2,"h":2},"rotated":false,"trimmed":false,"spriteSourceSize":{"x":0,"y":0,"w":2,"h":2},"sourceSize":{"w":2,"h":2}},"destructodiscexp005":{"frame":{"x":917,"y":473,"w":78,"h":76},"rotated":false,"trimmed":false,"spriteSourceSize":{"x":0,"y":0,"w":78,"h":76},"sourceSize":{"w":78,"h":76}},"attack025":{"frame":{"x":107,"y":486,"w":26,"h":54},"rotated":false,"trimmed":false,"spriteSourceSize":{"x":0,"y":0,"w":26,"h":54},"sourceSize":{"w":26,"h":54}},"attack024":{"frame":{"x":60,"y":488,"w":29,"h":52},"rotated":false,"trimmed":false,"spriteSourceSize":{"x":0,"y":0,"w":29,"h":52},"sourceSize":{"w":29,"h":52}},"attack026":{"frame":{"x":148,"y":488,"w":33,"h":52},"rotated":false,"trimmed":false,"spriteSourceSize":{"x":0,"y":0,"w":33,"h":52},"sourceSize":{"w":33,"h":52}},"destructodiscexp004":{"frame":{"x":852,"y":488,"w":56,"h":56},"rotated":false,"trimmed":false,"spriteSourceSize":{"x":0,"y":0,"w":56,"h":56},"sourceSize":{"w":56,"h":56}},"attack023":{"frame":{"x":12,"y":489,"w":32,"h":51},"rotated":false,"trimmed":false,"spriteSourceSize":{"x":0,"y":0,"w":32,"h":51},"sourceSize":{"w":32,"h":51}},"attack027":{"frame":{"x":193,"y":490,"w":36,"h":50},"rotated":false,"trimmed":false,"spriteSourceSize":{"x":0,"y":0,"w":36,"h":50},"sourceSize":{"w":36,"h":50}},"attack028":{"frame":{"x":238,"y":491,"w":38,"h":49},"rotated":false,"trimmed":false,"spriteSourceSize":{"x":0,"y":0,"w":38,"h":49},"sourceSize":{"w":38,"h":49}},"destructodiscexp002":{"frame":{"x":642,"y":503,"w":42,"h":42},"rotated":false,"trimmed":false,"spriteSourceSize":{"x":0,"y":0,"w":42,"h":42},"sourceSize":{"w":42,"h":42}},"destructodiscexp003":{"frame":{"x":700,"y":503,"w":141,"h":42},"rotated":false,"trimmed":false,"spriteSourceSize":{"x":0,"y":0,"w":141,"h":42},"sourceSize":{"w":141,"h":42}},"destructodiscexp001":{"frame":{"x":606,"y":506,"w":31,"h":32},"rotated":false,"trimmed":false,"spriteSourceSize":{"x":0,"y":0,"w":31,"h":32},"sourceSize":{"w":31,"h":32}},"sprite91":{"frame":{"x":294,"y":514,"w":7,"h":7},"rotated":false,"trimmed":false,"spriteSourceSize":{"x":0,"y":0,"w":7,"h":7},"sourceSize":{"w":7,"h":7}},"sprite95":{"frame":{"x":951,"y":549,"w":2,"h":2},"rotated":false,"trimmed":false,"spriteSourceSize":{"x":0,"y":0,"w":2,"h":2},"sourceSize":{"w":2,"h":2}},"sprite96":{"frame":{"x":959,"y":549,"w":2,"h":2},"rotated":false,"trimmed":false,"spriteSourceSize":{"x":0,"y":0,"w":2,"h":2},"sourceSize":{"w":2,"h":2}},"sprite97":{"frame":{"x":748,"y":558,"w":30,"h":11},"rotated":false,"trimmed":false,"spriteSourceSize":{"x":0,"y":0,"w":30,"h":11},"sourceSize":{"w":30,"h":11}},"sprite98":{"frame":{"x":795,"y":568,"w":1,"h":1},"rotated":false,"trimmed":false,"spriteSourceSize":{"x":0,"y":0,"w":1,"h":1},"sourceSize":{"w":1,"h":1}},"sprite99":{"frame":{"x":804,"y":568,"w":1,"h":1},"rotated":false,"trimmed":false,"spriteSourceSize":{"x":0,"y":0,"w":1,"h":1},"sourceSize":{"w":1,"h":1}},"sprite100":{"frame":{"x":217,"y":579,"w":35,"h":55},"rotated":false,"trimmed":false,"spriteSourceSize":{"x":0,"y":0,"w":35,"h":55},"sourceSize":{"w":35,"h":55}},"sprite101":{"frame":{"x":263,"y":579,"w":32,"h":55},"rotated":false,"trimmed":false,"spriteSourceSize":{"x":0,"y":0,"w":32,"h":55},"sourceSize":{"w":32,"h":55}},"sprite102":{"frame":{"x":303,"y":580,"w":43,"h":54},"rotated":false,"trimmed":false,"spriteSourceSize":{"x":0,"y":0,"w":43,"h":54},"sourceSize":{"w":43,"h":54}},"sprite103":{"frame":{"x":97,"y":581,"w":27,"h":53},"rotated":false,"trimmed":false,"spriteSourceSize":{"x":0,"y":0,"w":27,"h":53},"sourceSize":{"w":27,"h":53}},"sprite104":{"frame":{"x":359,"y":581,"w":35,"h":53},"rotated":false,"trimmed":false,"spriteSourceSize":{"x":0,"y":0,"w":35,"h":53},"sourceSize":{"w":35,"h":53}},"sprite105":{"frame":{"x":10,"y":583,"w":30,"h":51},"rotated":false,"trimmed":false,"spriteSourceSize":{"x":0,"y":0,"w":30,"h":51},"sourceSize":{"w":30,"h":51}},"sprite106":{"frame":{"x":55,"y":583,"w":29,"h":51},"rotated":false,"trimmed":false,"spriteSourceSize":{"x":0,"y":0,"w":29,"h":51},"sourceSize":{"w":29,"h":51}},"sprite107":{"frame":{"x":141,"y":587,"w":27,"h":47},"rotated":false,"trimmed":false,"spriteSourceSize":{"x":0,"y":0,"w":27,"h":47},"sourceSize":{"w":27,"h":47}},"destructodisc001":{"frame":{"x":483,"y":592,"w":60,"h":23},"rotated":false,"trimmed":false,"spriteSourceSize":{"x":0,"y":0,"w":60,"h":23},"sourceSize":{"w":60,"h":23}},"destructodisc002":{"frame":{"x":549,"y":592,"w":57,"h":23},"rotated":false,"trimmed":false,"spriteSourceSize":{"x":0,"y":0,"w":57,"h":23},"sourceSize":{"w":57,"h":23}},"sprite110":{"frame":{"x":190,"y":610,"w":7,"h":7},"rotated":false,"trimmed":false,"spriteSourceSize":{"x":0,"y":0,"w":7,"h":7},"sourceSize":{"w":7,"h":7}},"sprite111":{"frame":{"x":428,"y":610,"w":7,"h":7},"rotated":false,"trimmed":false,"spriteSourceSize":{"x":0,"y":0,"w":7,"h":7},"sourceSize":{"w":7,"h":7}},"sprite112":{"frame":{"x":10,"y":679,"w":30,"h":51},"rotated":false,"trimmed":false,"spriteSourceSize":{"x":0,"y":0,"w":30,"h":51},"sourceSize":{"w":30,"h":51}},"hit001":{"frame":{"x":104,"y":681,"w":44,"h":49},"rotated":false,"trimmed":false,"spriteSourceSize":{"x":0,"y":0,"w":44,"h":49},"sourceSize":{"w":44,"h":49}},"hit002":{"frame":{"x":154,"y":682,"w":34,"h":48},"rotated":false,"trimmed":false,"spriteSourceSize":{"x":0,"y":0,"w":34,"h":48},"sourceSize":{"w":34,"h":48}},"normalbombexp003":{"frame":{"x":750,"y":684,"w":72,"h":68},"rotated":false,"trimmed":false,"spriteSourceSize":{"x":0,"y":0,"w":72,"h":68},"sourceSize":{"w":72,"h":68}},"normalbombexp002":{"frame":{"x":672,"y":686,"w":62,"h":64},"rotated":false,"trimmed":false,"spriteSourceSize":{"x":0,"y":0,"w":62,"h":64},"sourceSize":{"w":62,"h":64}},"sprite118":{"frame":{"x":253,"y":688,"w":32,"h":40},"rotated":false,"trimmed":false,"spriteSourceSize":{"x":0,"y":0,"w":32,"h":40},"sourceSize":{"w":32,"h":40}},"sprite119":{"frame":{"x":52,"y":690,"w":40,"h":40},"rotated":false,"trimmed":false,"spriteSourceSize":{"x":0,"y":0,"w":40,"h":40},"sourceSize":{"w":40,"h":40}},"normalbomb001":{"frame":{"x":497,"y":691,"w":45,"h":54},"rotated":false,"trimmed":false,"spriteSourceSize":{"x":0,"y":0,"w":45,"h":54},"sourceSize":{"w":45,"h":54}},"normalbomb002":{"frame":{"x":553,"y":695,"w":48,"h":48},"rotated":false,"trimmed":false,"spriteSourceSize":{"x":0,"y":0,"w":48,"h":48},"sourceSize":{"w":48,"h":48}},"sprite122":{"frame":{"x":93,"y":699,"w":1,"h":1},"rotated":false,"trimmed":false,"spriteSourceSize":{"x":0,"y":0,"w":1,"h":1},"sourceSize":{"w":1,"h":1}},"sprite123":{"frame":{"x":200,"y":702,"w":43,"h":28},"rotated":false,"trimmed":false,"spriteSourceSize":{"x":0,"y":0,"w":43,"h":28},"sourceSize":{"w":43,"h":28}},"death001":{"frame":{"x":293,"y":705,"w":56,"h":29},"rotated":false,"trimmed":false,"spriteSourceSize":{"x":0,"y":0,"w":56,"h":29},"sourceSize":{"w":56,"h":29}},"sprite127":{"frame":{"x":372,"y":707,"w":7,"h":7},"rotated":false,"trimmed":false,"spriteSourceSize":{"x":0,"y":0,"w":7,"h":7},"sourceSize":{"w":7,"h":7}},"sprite128":{"frame":{"x":471,"y":710,"w":13,"h":15},"rotated":false,"trimmed":false,"spriteSourceSize":{"x":0,"y":0,"w":13,"h":15},"sourceSize":{"w":13,"h":15}},"sprite129":{"frame":{"x":466,"y":715,"w":1,"h":1},"rotated":false,"trimmed":false,"spriteSourceSize":{"x":0,"y":0,"w":1,"h":1},"sourceSize":{"w":1,"h":1}},"sprite130":{"frame":{"x":466,"y":719,"w":1,"h":1},"rotated":false,"trimmed":false,"spriteSourceSize":{"x":0,"y":0,"w":1,"h":1},"sourceSize":{"w":1,"h":1}},"normalbombexp001":{"frame":{"x":622,"y":704,"w":32,"h":28},"rotated":false,"trimmed":false,"spriteSourceSize":{"x":0,"y":0,"w":32,"h":28},"sourceSize":{"w":32,"h":28}},"longattacku001":{"frame":{"x":10,"y":774,"w":32,"h":52},"rotated":false,"trimmed":false,"spriteSourceSize":{"x":0,"y":0,"w":32,"h":52},"sourceSize":{"w":32,"h":52}},"longattacku002":{"frame":{"x":64,"y":774,"w":43,"h":52},"rotated":false,"trimmed":false,"spriteSourceSize":{"x":0,"y":0,"w":43,"h":52},"sourceSize":{"w":43,"h":52}},"longattacku003":{"frame":{"x":128,"y":775,"w":42,"h":51},"rotated":false,"trimmed":false,"spriteSourceSize":{"x":0,"y":0,"w":42,"h":51},"sourceSize":{"w":42,"h":51}},"longattacku004":{"frame":{"x":275,"y":775,"w":40,"h":51},"rotated":false,"trimmed":false,"spriteSourceSize":{"x":0,"y":0,"w":40,"h":51},"sourceSize":{"w":40,"h":51}},"sprite140":{"frame":{"x":326,"y":775,"w":80,"h":51},"rotated":false,"trimmed":false,"spriteSourceSize":{"x":0,"y":0,"w":80,"h":51},"sourceSize":{"w":80,"h":51}},"sprite141":{"frame":{"x":107,"y":804,"w":2,"h":1},"rotated":false,"trimmed":false,"spriteSourceSize":{"x":0,"y":0,"w":2,"h":1},"sourceSize":{"w":2,"h":1}},"sprite142":{"frame":{"x":110,"y":804,"w":1,"h":1},"rotated":false,"trimmed":false,"spriteSourceSize":{"x":0,"y":0,"w":1,"h":1},"sourceSize":{"w":1,"h":1}},"sprite143":{"frame":{"x":58,"y":805,"w":2,"h":1},"rotated":false,"trimmed":false,"spriteSourceSize":{"x":0,"y":0,"w":2,"h":1},"sourceSize":{"w":2,"h":1}},"sprite144":{"frame":{"x":62,"y":805,"w":2,"h":1},"rotated":false,"trimmed":false,"spriteSourceSize":{"x":0,"y":0,"w":2,"h":1},"sourceSize":{"w":2,"h":1}},"sprite145":{"frame":{"x":193,"y":841,"w":69,"h":79},"rotated":false,"trimmed":false,"spriteSourceSize":{"x":0,"y":0,"w":69,"h":79},"sourceSize":{"w":69,"h":79}},"sprite146":{"frame":{"x":120,"y":842,"w":63,"h":79},"rotated":false,"trimmed":false,"spriteSourceSize":{"x":0,"y":0,"w":63,"h":79},"sourceSize":{"w":63,"h":79}},"sprite147":{"frame":{"x":10,"y":870,"w":30,"h":50},"rotated":false,"trimmed":false,"spriteSourceSize":{"x":0,"y":0,"w":30,"h":50},"sourceSize":{"w":30,"h":50}},"sprite148":{"frame":{"x":68,"y":870,"w":31,"h":50},"rotated":false,"trimmed":false,"spriteSourceSize":{"x":0,"y":0,"w":31,"h":50},"sourceSize":{"w":31,"h":50}},"sprite149":{"frame":{"x":588,"y":927,"w":419,"h":128},"rotated":false,"trimmed":false,"spriteSourceSize":{"x":0,"y":0,"w":419,"h":128},"sourceSize":{"w":419,"h":128}},"longattackj007":{"frame":{"x":277,"y":955,"w":28,"h":54},"rotated":false,"trimmed":false,"spriteSourceSize":{"x":0,"y":0,"w":28,"h":54},"sourceSize":{"w":28,"h":54}},"longattackj004":{"frame":{"x":151,"y":956,"w":18,"h":51},"rotated":false,"trimmed":false,"spriteSourceSize":{"x":0,"y":0,"w":18,"h":51},"sourceSize":{"w":18,"h":51}},"longattackj008":{"frame":{"x":322,"y":956,"w":30,"h":57},"rotated":false,"trimmed":false,"spriteSourceSize":{"x":0,"y":0,"w":30,"h":57},"sourceSize":{"w":30,"h":57}},"longattackj009":{"frame":{"x":373,"y":956,"w":30,"h":57},"rotated":false,"trimmed":false,"spriteSourceSize":{"x":0,"y":0,"w":30,"h":57},"sourceSize":{"w":30,"h":57}},"longattackj005":{"frame":{"x":187,"y":958,"w":30,"h":48},"rotated":false,"trimmed":false,"spriteSourceSize":{"x":0,"y":0,"w":30,"h":48},"sourceSize":{"w":30,"h":48}},"longattackj006":{"frame":{"x":231,"y":958,"w":30,"h":48},"rotated":false,"trimmed":false,"spriteSourceSize":{"x":0,"y":0,"w":30,"h":48},"sourceSize":{"w":30,"h":48}},"sprite156":{"frame":{"x":171,"y":963,"w":1,"h":17},"rotated":false,"trimmed":false,"spriteSourceSize":{"x":0,"y":0,"w":1,"h":17},"sourceSize":{"w":1,"h":17}},"sprite157":{"frame":{"x":147,"y":965,"w":3,"h":14},"rotated":false,"trimmed":false,"spriteSourceSize":{"x":0,"y":0,"w":3,"h":14},"sourceSize":{"w":3,"h":14}},"longattackj002":{"frame":{"x":56,"y":967,"w":31,"h":52},"rotated":false,"trimmed":false,"spriteSourceSize":{"x":0,"y":0,"w":31,"h":52},"sourceSize":{"w":31,"h":52}},"longattackj003":{"frame":{"x":103,"y":967,"w":31,"h":52},"rotated":false,"trimmed":false,"spriteSourceSize":{"x":0,"y":0,"w":31,"h":52},"sourceSize":{"w":31,"h":52}},"longattackj011":{"frame":{"x":471,"y":968,"w":34,"h":51},"rotated":false,"trimmed":false,"spriteSourceSize":{"x":0,"y":0,"w":34,"h":51},"sourceSize":{"w":34,"h":51}},"longattackj012":{"frame":{"x":529,"y":968,"w":39,"h":51},"rotated":false,"trimmed":false,"spriteSourceSize":{"x":0,"y":0,"w":39,"h":51},"sourceSize":{"w":39,"h":51}},"longattackj001":{"frame":{"x":10,"y":973,"w":34,"h":46},"rotated":false,"trimmed":false,"spriteSourceSize":{"x":0,"y":0,"w":34,"h":46},"sourceSize":{"w":34,"h":46}},"sprite163":{"frame":{"x":427,"y":981,"w":8,"h":1},"rotated":false,"trimmed":false,"spriteSourceSize":{"x":0,"y":0,"w":8,"h":1},"sourceSize":{"w":8,"h":1}},"longattackj010":{"frame":{"x":411,"y":982,"w":51,"h":25},"rotated":false,"trimmed":false,"spriteSourceSize":{"x":0,"y":0,"w":51,"h":25},"sourceSize":{"w":51,"h":25}},"sprite165":{"frame":{"x":146,"y":983,"w":1,"h":8},"rotated":false,"trimmed":false,"spriteSourceSize":{"x":0,"y":0,"w":1,"h":8},"sourceSize":{"w":1,"h":8}},"sprite166":{"frame":{"x":172,"y":985,"w":1,"h":5},"rotated":false,"trimmed":false,"spriteSourceSize":{"x":0,"y":0,"w":1,"h":5},"sourceSize":{"w":1,"h":5}},"sprite167":{"frame":{"x":428,"y":1007,"w":5,"h":1},"rotated":false,"trimmed":false,"spriteSourceSize":{"x":0,"y":0,"w":5,"h":1},"sourceSize":{"w":5,"h":1}},"sprite168":{"frame":{"x":131,"y":1099,"w":26,"h":57},"rotated":false,"trimmed":false,"spriteSourceSize":{"x":0,"y":0,"w":26,"h":57},"sourceSize":{"w":26,"h":57}},"sprite169":{"frame":{"x":9,"y":1100,"w":27,"h":55},"rotated":false,"trimmed":false,"spriteSourceSize":{"x":0,"y":0,"w":27,"h":55},"sourceSize":{"w":27,"h":55}},"sprite170":{"frame":{"x":50,"y":1100,"w":29,"h":55},"rotated":false,"trimmed":false,"spriteSourceSize":{"x":0,"y":0,"w":29,"h":55},"sourceSize":{"w":29,"h":55}},"sprite171":{"frame":{"x":91,"y":1100,"w":27,"h":55},"rotated":false,"trimmed":false,"spriteSourceSize":{"x":0,"y":0,"w":27,"h":55},"sourceSize":{"w":27,"h":55}},"sprite172":{"frame":{"x":238,"y":1102,"w":35,"h":54},"rotated":false,"trimmed":false,"spriteSourceSize":{"x":0,"y":0,"w":35,"h":54},"sourceSize":{"w":35,"h":54}},"sprite173":{"frame":{"x":171,"y":1103,"w":31,"h":53},"rotated":false,"trimmed":false,"spriteSourceSize":{"x":0,"y":0,"w":31,"h":53},"sourceSize":{"w":31,"h":53}},"sprite174":{"frame":{"x":290,"y":1107,"w":37,"h":47},"rotated":false,"trimmed":false,"spriteSourceSize":{"x":0,"y":0,"w":37,"h":47},"sourceSize":{"w":37,"h":47}},"sprite175":{"frame":{"x":340,"y":1119,"w":35,"h":37},"rotated":false,"trimmed":false,"spriteSourceSize":{"x":0,"y":0,"w":35,"h":37},"sourceSize":{"w":35,"h":37}},"sprite176":{"frame":{"x":391,"y":1119,"w":35,"h":37},"rotated":false,"trimmed":false,"spriteSourceSize":{"x":0,"y":0,"w":35,"h":37},"sourceSize":{"w":35,"h":37}},"sprite177":{"frame":{"x":441,"y":1119,"w":35,"h":37},"rotated":false,"trimmed":false,"spriteSourceSize":{"x":0,"y":0,"w":35,"h":37},"sourceSize":{"w":35,"h":37}}},"meta":{"app":"https://www.leshylabs.com/apps/sstool/","version":"Leshy SpriteSheet Tool v0.8.4","image":"spritesheet.png","size":{"w":1013,"h":1206},"scale":1}}